MANIFEST.in
README.md
README.rst
requirements.txt
setup.py
cvulkan/__init__.py
cvulkan/jfilter.py
cvulkan/vulkan_generator.py
cvulkan/vulkanmodule.c
cvulkan.egg-info/PKG-INFO
cvulkan.egg-info/SOURCES.txt
cvulkan.egg-info/dependency_links.txt
cvulkan.egg-info/top_level.txt
cvulkan/example/frag.spv
cvulkan/example/shader.frag
cvulkan/example/shader.vert
cvulkan/example/vert.spv
cvulkan/template/converters.c
cvulkan/template/custom_functions.c
cvulkan/template/custom_structs.c
cvulkan/template/extension_functions.c
cvulkan/template/functions.c
cvulkan/template/header.c
cvulkan/template/init.c
cvulkan/template/macros.c
cvulkan/template/main.c
cvulkan/template/objects.c
cvulkan/template/init_unions/vkclearcolorvalue.c
cvulkan/template/init_unions/vkclearvalue.c